eefdata/__init__.py
eefdata/app.py
eefdata/src/__init__.py
eefdata/src/attributeIDs.py
eefdata/src/funcs.py
eef_data-0.59.dist-info/LICENSE
eef_data-0.59.dist-info/METADATA
eef_data-0.59.dist-info/WHEEL
eef_data-0.59.dist-info/entry_points.txt
eef_data-0.59.dist-info/top_level.txt
eef_data-0.59.dist-info/RECORD
