Metadata-Version: 2.1
Name: eef-data
Version: 0.59
Summary: UNKNOWN
Home-page: UNKNOWN
License: UNKNOWN
Platform: UNKNOWN
Requires-Python: >=3.10.6
License-File: LICENSE
Requires-Dist: pandas (==1.5.0)
Requires-Dist: prompt-toolkit (==3.0.30)
Requires-Dist: rich (==12.4.4)
Requires-Dist: toolz (==0.11.2)
Provides-Extra: full
Requires-Dist: numpy (==1.22.0) ; extra == 'full'
